[
  {
    "id": "cmek2epwd001wx5j7q9qx49a5",
    "quoteId": "QT-2025-0718-001",
    "date": "2025-07-17T20:00:00.000Z",
    "status": "Approved",
    "clientId": "cmek2epop0004x5j7m81cyrgz",
    "userId": null,
    "createdAt": "2025-08-20T10:25:32.317Z",
    "updatedAt": "2025-08-20T10:25:32.317Z",
    "product": "Business Card",
    "quantity": 1000,
    "sides": "1",
    "printing": "Digital",
    "colors": null
  },
  {
    "id": "cmek2epww0021x5j703n82450",
    "quoteId": "QT-2025-0718-002",
    "date": "2025-07-17T20:00:00.000Z",
    "status": "Pending",
    "clientId": "cmek2epwr001zx5j7zkdpllm8",
    "userId": null,
    "createdAt": "2025-08-20T10:25:32.336Z",
    "updatedAt": "2025-08-20T10:25:32.336Z",
    "product": "Art Book",
    "quantity": 250,
    "sides": "1",
    "printing": "Digital",
    "colors": null
  },
  {
    "id": "cmek2epxd0026x5j71rlvx9tw",
    "quoteId": "QT-2025-0719-003",
    "date": "2025-07-18T20:00:00.000Z",
    "status": "Rejected",
    "clientId": "cmek2epx70024x5j7knkhgxeq",
    "userId": null,
    "createdAt": "2025-08-20T10:25:32.353Z",
    "updatedAt": "2025-08-20T10:25:32.353Z",
    "product": "Poster A2",
    "quantity": 300,
    "sides": "1",
    "printing": "Digital",
    "colors": null
  },
  {
    "id": "cmek2epxt002bx5j7f82jxumw",
    "quoteId": "QT-2025-0720-004",
    "date": "2025-07-19T20:00:00.000Z",
    "status": "Approved",
    "clientId": "cmek2epxo0029x5j70l4yzcra",
    "userId": null,
    "createdAt": "2025-08-20T10:25:32.369Z",
    "updatedAt": "2025-08-20T10:25:32.369Z",
    "product": "Flyer A5",
    "quantity": 2000,
    "sides": "1",
    "printing": "Digital",
    "colors": null
  },
  {
    "id": "cmek2epyd002gx5j736tpmlo3",
    "quoteId": "QT-2025-0720-005",
    "date": "2025-07-19T20:00:00.000Z",
    "status": "Approved",
    "clientId": "cmek2epy7002ex5j7vhvd4iag",
    "userId": null,
    "createdAt": "2025-08-20T10:25:32.388Z",
    "updatedAt": "2025-08-20T10:25:32.388Z",
    "product": "Magazine",
    "quantity": 500,
    "sides": "1",
    "printing": "Digital",
    "colors": null
  },
  {
    "id": "cmek2epyp002lx5j782u8z8rf",
    "quoteId": "QT-2025-0721-006",
    "date": "2025-07-20T20:00:00.000Z",
    "status": "Pending",
    "clientId": "cmek2epym002jx5j720tijpkm",
    "userId": null,
    "createdAt": "2025-08-20T10:25:32.401Z",
    "updatedAt": "2025-08-20T10:25:32.401Z",
    "product": "Sticker Pack",
    "quantity": 500,
    "sides": "1",
    "printing": "Digital",
    "colors": null
  },
  {
    "id": "cmek2eq0c0030x5j7nh64b7la",
    "quoteId": "QT-2025-0722-009",
    "date": "2025-07-21T20:00:00.000Z",
    "status": "Approved",
    "clientId": "cmek2eq03002yx5j7qs86661g",
    "userId": null,
    "createdAt": "2025-08-20T10:25:32.460Z",
    "updatedAt": "2025-08-20T10:25:32.460Z",
    "product": "Menu Card",
    "quantity": 700,
    "sides": "1",
    "printing": "Digital",
    "colors": null
  },
  {
    "id": "cmek2eq0z0035x5j78d2bh52a",
    "quoteId": "QT-2025-0723-010",
    "date": "2025-08-19T20:00:00.000Z",
    "status": "Approved",
    "clientId": "cmek2eq0u0033x5j7eezs3wwm",
    "userId": "cmek2oic80002x5xjcvofcdxt",
    "createdAt": "2025-08-20T10:25:32.482Z",
    "updatedAt": "2025-08-20T18:11:55.780Z",
    "product": "Business Card",
    "quantity": 150,
    "sides": "1",
    "printing": "Digital",
    "colors": null
  },
  {
    "id": "cmekj5xca0013xfflnbl5ohpr",
    "quoteId": "QT-2025-0821-353",
    "date": "2025-08-20T18:14:34.344Z",
    "status": "Pending",
    "clientId": "cmekj5wmd0011xffl1gmkylyz",
    "userId": null,
    "createdAt": "2025-08-20T18:14:35.530Z",
    "updatedAt": "2025-08-20T18:14:35.530Z",
    "product": "Business Card",
    "quantity": 1000,
    "sides": "1",
    "printing": "Digital",
    "colors": null
  },
  {
    "id": "cmekilram0003xfflus48jf6p",
    "quoteId": "QT-2024-001",
    "date": "2025-08-19T20:00:00.000Z",
    "status": "Approved",
    "clientId": "cmekilqus0001xfflrr98j2ym",
    "userId": "cmekj0vxf0006xffl2xdoub1x",
    "createdAt": "2025-08-20T17:58:54.574Z",
    "updatedAt": "2025-08-20T18:23:51.586Z",
    "product": "Business Cards",
    "quantity": 1000,
    "sides": "Double-sided",
    "printing": "Full Color",
    "colors": null
  },
  {
    "id": "cmek39ntx000jx5xjpk1lqq87",
    "quoteId": "QT-2025-0820-796",
    "date": "2025-08-20T11:01:25.687Z",
    "status": "Rejected",
    "clientId": "cmek38mc7000bx5xj7m0r8vcw",
    "userId": "cmek2oic80002x5xjcvofcdxt",
    "createdAt": "2025-08-20T10:49:35.973Z",
    "updatedAt": "2025-08-20T18:34:33.535Z",
    "product": "Business Card",
    "quantity": 1000,
    "sides": "1",
    "printing": "Digital",
    "colors": null
  },
  {
    "id": "cmek38mmv000dx5xj81sjd9pk",
    "quoteId": "QT-2025-0820-259",
    "date": "2025-08-20T10:48:47.574Z",
    "status": "Approved",
    "clientId": "cmek38mc7000bx5xj7m0r8vcw",
    "userId": "cmek2oic80002x5xjcvofcdxt",
    "createdAt": "2025-08-20T10:48:47.768Z",
    "updatedAt": "2025-08-20T18:46:28.568Z",
    "product": "Business Card",
    "quantity": 1000,
    "sides": "1",
    "printing": "Digital",
    "colors": null
  },
  {
    "id": "cmek2epz5002qx5j701d8lfv6",
    "quoteId": "QT-2025-0721-007",
    "date": "2025-08-21T01:27:44.426Z",
    "status": "Approved",
    "clientId": "cmek2epz1002ox5j7r1giwxov",
    "userId": "cmekj0vxf0006xffl2xdoub1x",
    "createdAt": "2025-08-20T10:25:32.417Z",
    "updatedAt": "2025-08-21T03:44:09.048Z",
    "product": "Brochure",
    "quantity": 50,
    "sides": "1",
    "printing": "Digital",
    "colors": null
  },
  {
    "id": "cmenntj3g000112h1ou4g67gp",
    "quoteId": "QT-2025-0823-444",
    "date": "2025-08-22T22:48:12.524Z",
    "status": "Pending",
    "clientId": "cmennti3y000004iidvugak7k",
    "userId": null,
    "createdAt": "2025-08-22T22:48:13.804Z",
    "updatedAt": "2025-08-22T22:48:13.804Z",
    "product": "Flyer A5",
    "quantity": 1000,
    "sides": "1",
    "printing": "Digital",
    "colors": null
  },
  {
    "id": "cmennvcgo000912h1lncsghek",
    "quoteId": "QT-2025-0823-917",
    "date": "2025-08-22T22:49:37.312Z",
    "status": "Approved",
    "clientId": "cmennti3y000004iidvugak7k",
    "userId": null,
    "createdAt": "2025-08-22T22:49:38.520Z",
    "updatedAt": "2025-08-22T22:50:25.637Z",
    "product": "Flyer A5",
    "quantity": 1000,
    "sides": "1",
    "printing": "Digital",
    "colors": null
  },
  {
    "id": "cmenufp400001wwgyqzguvfj6",
    "quoteId": "QT-2025-0823-236",
    "date": "2025-08-23T01:53:25.275Z",
    "status": "Pending",
    "clientId": "cmenufo0n000004jo2uc82gp2",
    "userId": null,
    "createdAt": "2025-08-23T01:53:25.728Z",
    "updatedAt": "2025-08-23T01:53:25.728Z",
    "product": "Business Card",
    "quantity": 5000,
    "sides": "2",
    "printing": "Offset",
    "colors": null
  },
  {
    "id": "cmenugdpw0008wwgytzkc3ivk",
    "quoteId": "QT-2025-0823-526",
    "date": "2025-08-23T01:53:57.327Z",
    "status": "Pending",
    "clientId": "cmenufo0n000004jo2uc82gp2",
    "userId": null,
    "createdAt": "2025-08-23T01:53:57.620Z",
    "updatedAt": "2025-08-23T01:53:57.620Z",
    "product": "Business Card",
    "quantity": 5000,
    "sides": "2",
    "printing": "Offset",
    "colors": null
  },
  {
    "id": "cmeospsfh00011qh927mqbgzt",
    "quoteId": "QT-2025-0824-936",
    "date": "2025-08-23T17:53:06.276Z",
    "status": "Pending",
    "clientId": "cmeosprku000004jx97xe0cfe",
    "userId": null,
    "createdAt": "2025-08-23T17:53:03.533Z",
    "updatedAt": "2025-08-23T17:53:03.533Z",
    "product": "Business Card",
    "quantity": 1000,
    "sides": "1",
    "printing": "Digital",
    "colors": null
  },
  {
    "id": "cmer1rq2l000112fj4rs0gswt",
    "quoteId": "QT-2025-0825-969",
    "date": "2025-08-25T07:42:03.472Z",
    "status": "Pending",
    "clientId": "cmeosprku000004jx97xe0cfe",
    "userId": null,
    "createdAt": "2025-08-25T07:42:02.685Z",
    "updatedAt": "2025-08-25T07:42:02.685Z",
    "product": "Business Card",
    "quantity": 1000,
    "sides": "2",
    "printing": "Digital",
    "colors": null
  }
]